qoqo_iqm-0.11.2.dist-info/METADATA
qoqo_iqm-0.11.2.dist-info/WHEEL
qoqo_iqm-0.11.2.dist-info/licenses/LICENSE
qoqo_iqm/DEPENDENCIES
qoqo_iqm/LICENSE_FOR_BINARY_DISTRIBUTION
qoqo_iqm/OPENSSL_LICENSE
qoqo_iqm/PYTHON_LICENSE
qoqo_iqm/__init__.py
qoqo_iqm/qoqo_iqm.cpython-310-aarch64-linux-gnu.so
qoqo_iqm-0.11.2.dist-info/RECORD
